nudecrawler/__init__.py
nudecrawler/cache.py
nudecrawler/config.py
nudecrawler/exceptions.py
nudecrawler/localimage.py
nudecrawler/nudenet.py
nudecrawler/page.py
nudecrawler/remoteimage.py
nudecrawler/tgru.py
nudecrawler/unbuffered.py
nudecrawler/verbose.py
nudecrawler/version.py
nudecrawler/scripts/detect_image_aid.py
nudecrawler/scripts/detect_image_nsfw_api.py
nudecrawler/scripts/detect_image_nudenet.py
nudecrawler/scripts/detect_server_nudenet.py
nudecrawler/scripts/nudecrawler.py
nudecrawler/scripts/nudecrawler_makeurls.py
nudecrawler-0.3.28.dist-info/METADATA
nudecrawler-0.3.28.dist-info/WHEEL
nudecrawler-0.3.28.dist-info/entry_points.txt
nudecrawler-0.3.28.dist-info/RECORD
