Metadata-Version: 2.3
Name: nudecrawler
Version: 0.3.28
Summary: Crawl telegra.ph searching for nudes!
Project-URL: Homepage, https://github.com/yaroslaff/nudecrawler
Project-URL: Repository, https://github.com/yaroslaff/nudecrawler.git
Project-URL: Bug Tracker, https://github.com/yaroslaff/nudecrawler/issues
Project-URL: Changelog, https://github.com/yaroslaff/nudecrawler/blob/master/CHANGELOG.md
Author-email: Yaroslav Polyakov <yaroslaff@gmail.com>
License: MIT License
Keywords: crawl,crawler,find,nsfw,nsfw-recognition,nude,nudes,nudity-detection,onlyfans,scrape,scraper,scraping,search,spider,telegra-ph,tits,web-scraping,webscraping
Classifier: Development Status :: 5 - Production/Stable
Classifier: Environment :: Console
Classifier: Intended Audience :: End Users/Desktop
Classifier: License :: OSI Approved :: MIT License
Classifier: Programming Language :: Python :: 3.9
Classifier: Topic :: Games/Entertainment
Classifier: Topic :: Internet :: WWW/HTTP :: Indexing/Search
Classifier: Topic :: Scientific/Engineering :: Image Recognition
Requires-Python: >=3.9
Requires-Dist: beautifulsoup4>=4.12.0
Requires-Dist: evalidate>=2.0.3
Requires-Dist: flask
Requires-Dist: mudepy>=0.5.2
Requires-Dist: nudenet>=3.4.2
Requires-Dist: numpy<2.0.0
Requires-Dist: pillow>=9.4.0
Requires-Dist: pytest>=7.2.2
Requires-Dist: python-daemon>=3.0.1
Requires-Dist: python-dotenv>=1.0.0
Requires-Dist: requests>=2.28.2
Requires-Dist: rich
Requires-Dist: toml
Requires-Dist: transliterate>=1.10.2
